quadroots/__init__.py
quadroots/quadroots.py
quadroots-0.0.13.dist-info/LICENSE
quadroots-0.0.13.dist-info/METADATA
quadroots-0.0.13.dist-info/WHEEL
quadroots-0.0.13.dist-info/top_level.txt
quadroots-0.0.13.dist-info/RECORD
