Metadata-Version: 2.1
Name: quadroots
Version: 0.0.13
Summary: Calculating roots of quadratic equations
Home-page: UNKNOWN
Author: Shaun Porwal
Author-email: shaun.porwal@gmail.com
License: UNKNOWN
Keywords: python,quadratic,roots,calculator
Platform: UNKNOWN
Classifier: Development Status :: 1 - Planning
Classifier: Intended Audience :: Developers
Classifier: Programming Language :: Python :: 3
Classifier: Operating System :: Unix
Classifier: Operating System :: MacOS :: MacOS X
Classifier: Operating System :: Microsoft :: Windows
License-File: LICENSE
Requires-Dist: math
Requires-Dist: cmath
Requires-Dist: re
Requires-Dist: argparse
